scopesim_templates/__init__.py
scopesim_templates/calibration/__init__.py
scopesim_templates/calibration/calibration.py
scopesim_templates/defaults.yaml
scopesim_templates/extragalactic/__init__.py
scopesim_templates/extragalactic/agns.py
scopesim_templates/extragalactic/clusters.py
scopesim_templates/extragalactic/exgal_models.py
scopesim_templates/extragalactic/galaxies.py
scopesim_templates/extragalactic/galaxy_utils.py
scopesim_templates/extragalactic/quasars.py
scopesim_templates/extragalactic/spiral_two_component.fits.bz2
scopesim_templates/metis/__init__.py
scopesim_templates/metis/laser.py
scopesim_templates/metis/pinhole_mask.py
scopesim_templates/micado/__init__.py
scopesim_templates/micado/cluster.py
scopesim_templates/micado/darkness.py
scopesim_templates/micado/data/masterlinelist_2.1.txt
scopesim_templates/micado/flatlamp.py
scopesim_templates/micado/pinhole_masks.py
scopesim_templates/micado/spectral_calibrations.py
scopesim_templates/micado/viking_fields/__init__.py
scopesim_templates/micado/viking_fields/cat_illum.dat
scopesim_templates/micado/viking_fields/cat_science.dat
scopesim_templates/micado/viking_fields/cat_stdstar.dat
scopesim_templates/micado/viking_fields/faintgal_1.dat
scopesim_templates/micado/viking_fields/faintgal_2.dat
scopesim_templates/micado/viking_fields/faintgal_3.dat
scopesim_templates/micado/viking_fields/field_illum.eps
scopesim_templates/micado/viking_fields/field_science.eps
scopesim_templates/micado/viking_fields/field_stdstar.eps
scopesim_templates/micado/viking_fields/readme.rst
scopesim_templates/micado/viking_fields/viking_fields.py
scopesim_templates/misc/__init__.py
scopesim_templates/misc/misc.py
scopesim_templates/rc.py
scopesim_templates/stellar/__init__.py
scopesim_templates/stellar/cluster_utils.py
scopesim_templates/stellar/clusters.py
scopesim_templates/stellar/imf.py
scopesim_templates/stellar/mamajek.dat
scopesim_templates/stellar/mamajek_alt.dat
scopesim_templates/stellar/stars_utils.py
scopesim_templates-0.7.0.dist-info/LICENSE
scopesim_templates-0.7.0.dist-info/METADATA
scopesim_templates-0.7.0.dist-info/WHEEL
scopesim_templates-0.7.0.dist-info/RECORD
