Metadata-Version: 2.3
Name: ScopeSim_Templates
Version: 0.7.0
Summary: On-sky source templates for ScopeSim
License: GPL-3.0-or-later
Keywords: astronomy
Author: Astar Vienna
Author-email: astar.astro@univie.ac.at
Maintainer: Kieran Leschinski
Maintainer-email: kieran.leschinski@unive.ac.at
Requires-Python: >=3.10,<3.14
Classifier: Intended Audience :: Science/Research
Classifier: License :: OSI Approved :: GNU General Public License v3 or later (GPLv3+)
Classifier: Operating System :: OS Independent
Classifier: Programming Language :: Python :: 3
Classifier: Programming Language :: Python :: 3.10
Classifier: Programming Language :: Python :: 3.11
Classifier: Programming Language :: Python :: 3.12
Classifier: Programming Language :: Python :: 3.13
Classifier: Topic :: Scientific/Engineering :: Astronomy
Requires-Dist: astar-utils (>=0.4.0,<1.0)
Requires-Dist: astropy (>=6.1.5,<7.0.0)
Requires-Dist: beautifulsoup4 (>=4.13.3,<5.0.0)
Requires-Dist: docutils (>=0.19)
Requires-Dist: lxml (>=5.2.2,<6.0.0)
Requires-Dist: matplotlib (>=3.10.1,<4.0.0)
Requires-Dist: numpy (>=1.26.4,<2.3.0)
Requires-Dist: pyckles (>=0.5.0,<1.0)
Requires-Dist: pyyaml (>=6.0.2,<7.0.0)
Requires-Dist: scipy (>=1.14.1,<2.0.0)
Requires-Dist: scopesim (>=0.10.0,<0.12.0)
Requires-Dist: spextra (>=0.42.0,<1.0)
Requires-Dist: synphot (>=1.5.0,<2.0.0)
Project-URL: Bug Tracker, https://github.com/AstarVienna/ScopeSim_Templates/issues
Project-URL: Changelog, https://github.com/AstarVienna/ScopeSim_Templates/releases
Project-URL: Documentation, https://scopesim-templates.readthedocs.io/
Project-URL: Repository, https://github.com/AstarVienna/ScopeSim_Templates/
